carrion/__about__.py
carrion/__init__.py
carrion/argparser.py
carrion/carrion.py
carrion-0.0.1.dist-info/METADATA
carrion-0.0.1.dist-info/WHEEL
carrion-0.0.1.dist-info/licenses/LICENSE.txt
carrion-0.0.1.dist-info/RECORD
